{
    "students": [
        {
            "last_name": "Ivanov",
            "first_name": "Ivan",
            "patronymic": "Ivanovich",
            "gender": "Male",
            "passport": "1234 567890",
            "address": "Moscow",
            "parents": [],
            "group": null
        },
        {
            "last_name": "Petrova",
            "first_name": "Maria",
            "patronymic": "Sergeevna",
            "gender": "Female",
            "passport": "5678 123456",
            "address": "Saint Petersburg",
            "parents": [],
            "group": null
        }
    ],
    "teachers": [
        {
            "last_name": "Sidorov",
            "first_name": "Petr",
            "patronymic": "Vasilievich",
            "gender": "Male",
            "passport": "9876 543210",
            "address": "Kazan",
            "department": "Mathematics",
            "position": "Professor"
        },
        {
            "last_name": "Smirnova",
            "first_name": "Olga",
            "patronymic": "Ivanovna",
            "gender": "Female",
            "passport": "5432 109876",
            "address": "Novosibirsk",
            "department": "Physics",
            "position": "Associate Professor"
        }
    ],
    "departments": [
        {
            "name": "Mathematics",
            "head_teacher": 